l0n0lc/Py转Cpp转译器.py
l0n0lc/__init__.py
l0n0lc/ast访问者.py
l0n0lc/cpp类型.py
l0n0lc/cpp编译器.py
l0n0lc/std_array.py
l0n0lc/std_map.py
l0n0lc/std_set.py
l0n0lc/std_vector.py
l0n0lc/代码生成.py
l0n0lc/即时编译.py
l0n0lc/变量管理器.py
l0n0lc/基础映射.py
l0n0lc/基础混入.py
l0n0lc/容器构建器.py
l0n0lc/工具.py
l0n0lc/异常.py
l0n0lc/日志工具.py
l0n0lc/类型转换.py
l0n0lc/类支持.py
l0n0lc/类方法信息.py
l0n0lc/编译管理器.py
l0n0lc/表达式处理.py
l0n0lc/转译器工具.py
l0n0lc/通用工具.py
l0n0lc-1.2.0.dist-info/licenses/LICENSE
l0n0lc-1.2.0.dist-info/METADATA
l0n0lc-1.2.0.dist-info/WHEEL
l0n0lc-1.2.0.dist-info/top_level.txt
l0n0lc-1.2.0.dist-info/RECORD
