Metadata-Version: 2.4
Name: l0n0lc
Version: 1.2.0
Summary: 一个将python函数翻译为c++函数并运行的jit编译器
Classifier: Programming Language :: Python :: 3
Requires-Python: >=3.10
License-File: LICENSE
Dynamic: license-file
